README.txt
setup.cfg
setup.py
collective/__init__.py
collective.personaltags.egg-info/PKG-INFO
collective.personaltags.egg-info/SOURCES.txt
collective.personaltags.egg-info/dependency_links.txt
collective.personaltags.egg-info/entry_points.txt
collective.personaltags.egg-info/namespace_packages.txt
collective.personaltags.egg-info/not-zip-safe
collective.personaltags.egg-info/paster_plugins.txt
collective.personaltags.egg-info/requires.txt
collective.personaltags.egg-info/top_level.txt
collective/personaltags/README.txt
collective/personaltags/__init__.py
collective/personaltags/configure.zcml
collective/personaltags/interfaces.py
collective/personaltags/tests.py
collective/personaltags/behavior/__init__.py
collective/personaltags/behavior/configure.zcml
collective/personaltags/browser/__init__.py
collective/personaltags/browser/manage.py
collective/personaltags/browser/manage_templates/managetags.pt
collective/personaltags/content/__init__.py
collective/personaltags/content/configure.zcml
collective/personaltags/controlpanel/__init__.py
collective/personaltags/controlpanel/available_managers.py
collective/personaltags/controlpanel/configure.zcml
collective/personaltags/controlpanel/controlpanel.py
collective/personaltags/controlpanel/vocabularies.py
collective/personaltags/demo_manager/__init__.py
collective/personaltags/demo_manager/demo_manager.py
collective/personaltags/demo_manager/demo_storage.py
collective/personaltags/demo_manager/demo_view.py
collective/personaltags/demo_manager/demo_view_templates/listtags.pt
collective/personaltags/portlet/__init__.py
collective/personaltags/portlet/configure.zcml
collective/personaltags/portlet/mytags.py
collective/personaltags/portlet/templates/mytags.pt
collective/personaltags/profiles/default/controlpanel.xml
collective/personaltags/profiles/default/cssregistry.xml
collective/personaltags/profiles/default/jsregistry.xml
collective/personaltags/profiles/default/metadata.xml
collective/personaltags/profiles/default/portlets.xml
collective/personaltags/profiles/default/propertiestool.xml
collective/personaltags/profiles/default/registry.xml
collective/personaltags/profiles/default/types.xml
collective/personaltags/profiles/default/viewlets.xml
collective/personaltags/profiles/default/types/collective.personaltags.demo_storage.xml
collective/personaltags/static/jquery.autocomplete.css
collective/personaltags/static/jquery.autocomplete.js
