Metadata-Version: 1.0
Name: collective.personaltags
Version: 1.0
Summary: Track content using personal tags
Home-page: http://svn.plone.org/svn/collective/
Author: Kevin Gill
Author-email: kevin@movieextras.ie
License: GPL
Keywords: Plone,Plone4
Platform: UNKNOWN
Classifier: Framework :: Plone
Classifier: Programming Language :: Python
